django_stubs_ext/__init__.py
django_stubs_ext/aliases.py
django_stubs_ext/annotations.py
django_stubs_ext/patch.py
django_stubs_ext/py.typed
django_stubs_ext/types.py
django_stubs_ext_adb-0.7.0.dist-info/METADATA
django_stubs_ext_adb-0.7.0.dist-info/WHEEL
django_stubs_ext_adb-0.7.0.dist-info/top_level.txt
django_stubs_ext_adb-0.7.0.dist-info/RECORD
