Metadata-Version: 2.1
Name: django-stubs-ext-adb
Version: 0.7.0
Summary: Monkey-patching and extensions for django-stubs
Home-page: https://github.com/adambirds/django-stubs
Author: Adam Birds
Author-email: enquiries@adbwebdesigns.co.uk
Maintainer: Adam Birds
Maintainer-email: enquiries@adbwebdesigns.co.uk
License: MIT
Project-URL: Release notes, https://github.com/adambirds/django-stubs/releases
Classifier: License :: OSI Approved :: MIT License
Classifier: Operating System :: OS Independent
Classifier: Programming Language :: Python :: 3.7
Classifier: Programming Language :: Python :: 3.8
Classifier: Programming Language :: Python :: 3.9
Classifier: Programming Language :: Python :: 3.10
Classifier: Programming Language :: Python :: 3.11
Classifier: Typing :: Typed
Classifier: Framework :: Django
Classifier: Framework :: Django :: 2.2
Classifier: Framework :: Django :: 3.0
Classifier: Framework :: Django :: 3.1
Classifier: Framework :: Django :: 3.2
Classifier: Framework :: Django :: 4.0
Classifier: Framework :: Django :: 4.1
Requires-Python: >=3.7
Requires-Dist: django
Requires-Dist: typing-extensions
